{
    "study_name": "ManiMamba_Weather_pl192",
    "version": "v4",
    "best_value": 0.21190348267555237,
    "best_params": {
        "e_layers": 3,
        "batch_size": 32,
        "d_model": 128,
        "d_state": 2,
        "expand": 2,
        "epsilon": 0.0001,
        "cov_window": 8,
        "cov_stride": 16,
        "cov_rank": 0,
        "geo_d_model": 256,
        "geo_d_state": 16,
        "geo_d_conv": 4,
        "geo_expand": 2,
        "weight_decay": 1e-06,
        "learning_rate": 0.0001083,
        "train_epochs": 15,
        "warmup_epochs": 3,
        "patience": 5,
        "dropout": 0.2,
        "seed": 2023
    },
    "best_trial_number": 15,
    "best_trial_user_attrs": {
        "mse": 0.21190348267555237,
        "mae": 0.25276342034339905,
        "checkpoint": null,
        "arch_signature": "128|0|3|2|1|0.0001|8|16|0|256|16|4|1",
        "cuda_accel_overhead_mb": 946.107421875
    }
}